seedphase/__init__.py
seedphase/cli.py
seedphase/generator.py
seedphase-2.2.0.dist-info/METADATA
seedphase-2.2.0.dist-info/WHEEL
seedphase-2.2.0.dist-info/entry_points.txt
seedphase-2.2.0.dist-info/top_level.txt
seedphase-2.2.0.dist-info/RECORD
