Metadata-Version: 2.4
Name: seedphase
Version: 2.2.0
Summary: Password-protected BIP39 seed phrase generator
Author: Your Name
Requires-Python: >=3.8
Requires-Dist: bip-utils
Dynamic: author
Dynamic: requires-dist
Dynamic: requires-python
Dynamic: summary
